{
  "$schema": "http://json-schema.org/schema#",
  "$id": "http://www.ibm.com/dba/projects/PDQ/CD_HRPDQ.json",
  "title": "PDQ Document Type Definitions",
  "lastUpdatDate": "",
  "lastUpdate": "",
  "comment": "This is a Doc Type Definition showing some different property types",
  "baForDeployment": false,
  "definitions": {
    "HRPDQ": {
      "$id": "#HRPDQ",
      "title": "HRPDQ",
      "allOf": [
        {
          "$ref": "http://www.ibm.com/dba/schemas/#systemDocument"
        },
        {
          "type": "object",
          "description": "",
          "baclass": {
            "caDocTypeId": "e95583c8-e41b-406c-b9ec-12eb300630c4",
            "defaultRetentionPeriod": "Indefinite",
            "retentionPeriodUnits": ""
          },
          "properties": {}
        }
      ]
    }
  }
}